say_hello/__init__.py
say_hello/hello.py
say_hello_toto-0.0.1.dist-info/METADATA
say_hello_toto-0.0.1.dist-info/RECORD
say_hello_toto-0.0.1.dist-info/WHEEL
say_hello_toto-0.0.1.dist-info/entry_points.txt
say_hello_toto-0.0.1.dist-info/top_level.txt
